{
  "nodes": [
    {
      "id": "prescription1-1",
      "drugId": "R03CC02",
      "drugType": "베타2 작용제",
      "labelKo": "살부타몰",
      "labelEn": "Salbutamol",
      "efficacy": ["기관지 확장", "천식 완화"]
    },
    {
      "id": "prescription1-2",
      "drugId": "N02BE01",
      "drugType": "아세트 아미노펜",
      "labelKo": "타이레놀",
      "labelEn": "Tylenol",
      "efficacy": ["통증 완화", "해열"]
    },
    {
      "id": "reaction1-1",
      "label": "심계항진",
      "explain": {
        "발생 빈도": "드물(0.1-1%)",
        "증상 예시": "빠른 심장박동, 두근거림"
      },
      "alert": "심장 질환자 주의"
    },
    {
      "id": "reaction1-2",
      "label": "간 기능 저하",
      "explain": {
        "발생 빈도": "매우 드물(<0.1%)",
        "증상 예시": "황달, 어두운 소변"
      },
      "alert": "간 기능 저하 환자 주의"
    },
    {
      "id": "prescription2-1",
      "drugId": "C07AB03",
      "drugType": "베타차단제",
      "labelKo": "아테놀롤",
      "labelEn": "Atenolol",
      "efficacy": ["심박수 조절", "고혈압 조절"]
    },
    {
      "id": "prescription2-2",
      "drugId": "A05BA03",
      "drugType": "간 보호제",
      "labelKo": "실리마린",
      "labelEn": "Silymarin",
      "efficacy": ["간 보호", "항산화 작용"]
    },
    {
      "id": "reaction2-1",
      "label": "저혈압",
      "explain": {
        "발생 빈도": "혼합(1-10%)",
        "증상 예시": "어지러움, 피로, 저혈압"
      },
      "alert": "저혈압 증상 모니터링 필요"
    },
    {
      "id": "reaction2-2",
      "label": "피로",
      "explain": {
        "발생 빈도": "혼합(1-10%)",
        "증상 예시": "피로, 무기력"
      },
      "alert": "휴식 및 적절한 수면 필요"
    }
  ],
  "edges": [
    {
      "from": "prescription1-1",
      "to": "reaction1-1"
    },
    {
      "from": "prescription1-2",
      "to": "reaction1-2"
    },
    {
      "from": "reaction1-1",
      "to": "prescription2-1"
    },
    {
      "from": "reaction1-2",
      "to": "prescription2-2"
    },
    {
      "from": "prescription2-1",
      "to": "reaction2-1"
    },
    {
      "from": "prescription2-2",
      "to": "reaction2-2"
    }
  ],
  "review": "마동석 환자는 호흡곤란과 두통으로 인해 살부타몰(베타2 작용제)과 타이레놀(아세트아미노펜)이 처방될 수 있습니다. 살부타몰은 기관지 확장과 천식 완화에 효과적이지만, 심계항진과 간 기능 저하 등의 부작용이 있을 수 있습니다. 이를 조절하기 위해 아테놀롤(베타차단제)과 실리마린(간 보호제)이 추가 처방될 수 있으며, 저혈압과 피로 등의 부작용을 모니터링해야 합니다. 정기적인 건강 검진과 휴식이 필요합니다."
}
